dodgy/__init__.py
dodgy/__main__.py
dodgy/__pkginfo__.py
dodgy/checks.py
dodgy/run.py
dodgy-0.2.0.dist-info/LICENSE
dodgy-0.2.0.dist-info/METADATA
dodgy-0.2.0.dist-info/WHEEL
dodgy-0.2.0.dist-info/entry_points.txt
dodgy-0.2.0.dist-info/top_level.txt
dodgy-0.2.0.dist-info/RECORD
