Metadata-Version: 2.1
Name: dodgy
Version: 0.2.0
Summary: Dodgy: Searches for dodgy looking lines in Python code
Home-page: https://github.com/landscapeio/dodgy
Author: landscape.io
Author-email: code@landscape.io
License: MIT
Keywords: check for suspicious code
Platform: UNKNOWN
Classifier: Development Status :: 7 - Inactive
Classifier: Environment :: Console
Classifier: Intended Audience :: Developers
Classifier: License :: OSI Approved :: MIT License
Classifier: Operating System :: Unix
Classifier: Topic :: Software Development :: Quality Assurance
Classifier: Programming Language :: Python :: 3.3
Classifier: Programming Language :: Python :: 3.4
Classifier: Programming Language :: Python :: 3.5
Classifier: Programming Language :: Python :: 3.6
Classifier: Programming Language :: Python :: 3.7
Classifier: Programming Language :: Python :: 3.8
